reverse_image_search/__init__.py
reverse_image_search/cli.py
reverse_image_search/config.py
reverse_image_search/search.py
reverse_image_search/spinner.py
reverse_image_search-0.2.1.dist-info/entry_points.txt
reverse_image_search-0.2.1.dist-info/WHEEL
reverse_image_search-0.2.1.dist-info/METADATA
reverse_image_search-0.2.1.dist-info/RECORD
