Metadata-Version: 2.1
Name: reverse-image-search
Version: 0.2.1
Summary: Reverse Image Search
Author: Your Name
Author-email: you@example.com
Requires-Python: >=3.8,<4.0
Classifier: Programming Language :: Python :: 3
Classifier: Programming Language :: Python :: 3.8
Classifier: Programming Language :: Python :: 3.9
Requires-Dist: joblib (>=1.0.1,<2.0.0)
Requires-Dist: opencv-python (>=4.5.2,<5.0.0)
Requires-Dist: scikit-image (>=0.18.1,<0.19.0)
Requires-Dist: tabulate (>=0.8.9,<0.9.0)
